s3ac.py
s3ac-0.0.3.dist-info/METADATA
s3ac-0.0.3.dist-info/WHEEL
s3ac-0.0.3.dist-info/licenses/LICENSE
s3ac-0.0.3.dist-info/RECORD
