Metadata-Version: 2.1
Name: s3ac
Version: 0.0.3
Summary: Autocomplete s3 URIs in IPython.
Project-URL: Homepage, https://github.com/swidoff/s3ac
Project-URL: Bug Tracker, https://github.com/swidoff/s3ac/issues
Author-email: Seth Widoff <swidoff@gmail.com>
License: MIT License
Classifier: License :: OSI Approved :: MIT License
Classifier: Operating System :: OS Independent
Classifier: Programming Language :: Python :: 3
Requires-Python: >=3.8
Requires-Dist: boto3
